unicef_attachments/__init__.py
unicef_attachments/admin.py
unicef_attachments/fields.py
unicef_attachments/models.py
unicef_attachments/permissions.py
unicef_attachments/serializers.py
unicef_attachments/urls.py
unicef_attachments/utils.py
unicef_attachments/validators.py
unicef_attachments/views.py
unicef_attachments/migrations/0001_initial.py
unicef_attachments/migrations/0002_attachmentlink.py
unicef_attachments/migrations/0003_auto_20190227_1332.py
unicef_attachments/migrations/0004_filetype_group.py
unicef_attachments/migrations/0005_auto_20190705_1746.py
unicef_attachments/migrations/0006_auto_20211123_2120.py
unicef_attachments/migrations/0007_alter_attachment_hyperlink.py
unicef_attachments/migrations/0008_attachment_is_active.py
unicef_attachments/migrations/__init__.py
unicef_attachments-0.12.dist-info/LICENSE
unicef_attachments-0.12.dist-info/METADATA
unicef_attachments-0.12.dist-info/WHEEL
unicef_attachments-0.12.dist-info/top_level.txt
unicef_attachments-0.12.dist-info/RECORD
